Workbook

Sheet Member check
A1: Reperformance check: liability for ONE member (must match Python)
A3: Age today | B3: 45 | I3: Liability, Excel (Rs) | J3: =SUM(G21:G101) -> 7315530
A4: Salary today (Rs) | B4: 1200000 | I4: Liability, Python (Rs) | J4: 7315530
A5: Years of service today | B5: 23 | I5: Difference (Rs) | J5: =J3-J4 -> 9.3336217e-05
A6: Retirement age | B6: 60 | I6: Match? | J6: =IF(ABS(J5)<1,"YES","NO") -> YES
A7: Pension accrual per year of service | B7: =1/60 -> 0.016666667
A8: Salary growth | B8: 0.06
A9: Discount rate | B9: 0.07
A10: Pension increase | B10: 0
A11: Last age in table | B11: 115
A14: Years to retirement | B14: =B6-B3 -> 15
A15: Final salary (Rs) | B15: =B4*(1+B8)^B14 -> 2875869.8
A16: Yearly pension at retirement (Rs) | B16: =B7*B15*(B5+B14) -> 1821384.2
A18: Blue = inputs you can change. Everything else is a live formula.
A20: Years from now (s) | B20: Age at s | C20: Pension payable? (1/0) | D20: Chance alive at s (from IAI table) | E20: Expected pension paid (Rs) | F20: Discount factor | G20: Present value (Rs)
A21: 0 | B21: =$B$3+A21 -> 45 | C21: =IF(AND(A21>=$B$14,B21<=$B$11),1,0) -> 0 | D21: =IFERROR(INDEX('IIAMT 2012-15'!$C$2:$C$98,MATCH(B21,'IIAMT 2012-15'!$A$2:$A$98,0))/INDEX('IIAMT 2012-15'!$C$2:$C$98,MATCH($B$3,'IIAMT 2012-15'!$A$2:$A$98,0)),0) -> 1 | E21: =C21*$B$16*(1+$B$10)^(A21-$B$14)*D21 -> 0 | F21: =(1+$B$9)^(-A21) -> 1 | G21: =E21*F21 -> 0
A22: 1 | B22: =$B$3+A22 -> 46 | C22: =IF(AND(A22>=$B$14,B22<=$B$11),1,0) -> 0 | D22: =IFERROR(INDEX('IIAMT 2012-15'!$C$2:$C$98,MATCH(B22,'IIAMT 2012-15'!$A$2:$A$98,0))/INDEX('IIAMT 2012-15'!$C$2:$C$98,MATCH($B$3,'IIAMT 2012-15'!$A$2:$A$98,0)),0) -> 0.998185 | E22: =C22*$B$16*(1+$B$10)^(A22-$B$14)*D22 -> 0 | F22: =(1+$B$9)^(-A22) -> 0.93457944 | G22: =E22*F22 -> 0
A23: 2 | B23: =$B$3+A23 -> 47 | C23: =IF(AND(A23>=$B$14,B23<=$B$11),1,0) -> 0 | D23: =IFERROR(INDEX('IIAMT 2012-15'!$C$2:$C$98,MATCH(B23,'IIAMT 2012-15'!$A$2:$A$98,0))/INDEX('IIAMT 2012-15'!$C$2:$C$98,MATCH($B$3,'IIAMT 2012-15'!$A$2:$A$98,0)),0) -> 0.99622456 | E23: =C23*$B$16*(1+$B$10)^(A23-$B$14)*D23 -> 0 | F23: =(1+$B$9)^(-A23) -> 0.87343873 | G23: =E23*F23 -> 0
A24: 3 | B24: =$B$3+A24 -> 48 | C24: =IF(AND(A24>=$B$14,B24<=$B$11),1,0) -> 0 | D24: =IFERROR(INDEX('IIAMT 2012-15'!$C$2:$C$98,MATCH(B24,'IIAMT 2012-15'!$A$2:$A$98,0))/INDEX('IIAMT 2012-15'!$C$2:$C$98,MATCH($B$3,'IIAMT 2012-15'!$A$2:$A$98,0)),0) -> 0.99410759 | E24: =C24*$B$16*(1+$B$10)^(A24-$B$14)*D24 -> 0 | F24: =(1+$B$9)^(-A24) -> 0.81629788 | G24: =E24*F24 -> 0
A25: 4 | B25: =$B$3+A25 -> 49 | C25: =IF(AND(A25>=$B$14,B25<=$B$11),1,0) -> 0 | D25: =IFERROR(INDEX('IIAMT 2012-15'!$C$2:$C$98,MATCH(B25,'IIAMT 2012-15'!$A$2:$A$98,0))/INDEX('IIAMT 2012-15'!$C$2:$C$98,MATCH($B$3,'IIAMT 2012-15'!$A$2:$A$98,0)),0) -> 0.99181915 | E25: =C25*$B$16*(1+$B$10)^(A25-$B$14)*D25 -> 0 | F25: =(1+$B$9)^(-A25) -> 0.76289521 | G25: =E25*F25 -> 0
A26: 5 | B26: =$B$3+A26 -> 50 | C26: =IF(AND(A26>=$B$14,B26<=$B$11),1,0) -> 0 | D26: =IFERROR(INDEX('IIAMT 2012-15'!$C$2:$C$98,MATCH(B26,'IIAMT 2012-15'!$A$2:$A$98,0))/INDEX('IIAMT 2012-15'!$C$2:$C$98,MATCH($B$3,'IIAMT 2012-15'!$A$2:$A$98,0)),0) -> 0.98934456 | E26: =C26*$B$16*(1+$B$10)^(A26-$B$14)*D26 -> 0 | F26: =(1+$B$9)^(-A26) -> 0.71298618 | G26: =E26*F26 -> 0
A27: 6 | B27: =$B$3+A27 -> 51 | C27: =IF(AND(A27>=$B$14,B27<=$B$11),1,0) -> 0 | D27: =IFERROR(INDEX('IIAMT 2012-15'!$C$2:$C$98,MATCH(B27,'IIAMT 2012-15'!$A$2:$A$98,0))/INDEX('IIAMT 2012-15'!$C$2:$C$98,MATCH($B$3,'IIAMT 2012-15'!$A$2:$A$98,0)),0) -> 0.98666839 | E27: =C27*$B$16*(1+$B$10)^(A27-$B$14)*D27 -> 0 | F27: =(1+$B$9)^(-A27) -> 0.66634222 | G27: =E27*F27 -> 0
A28: 7 | B28: =$B$3+A28 -> 52 | C28: =IF(AND(A28>=$B$14,B28<=$B$11),1,0) -> 0 | D28: =IFERROR(INDEX('IIAMT 2012-15'!$C$2:$C$98,MATCH(B28,'IIAMT 2012-15'!$A$2:$A$98,0))/INDEX('IIAMT 2012-15'!$C$2:$C$98,MATCH($B$3,'IIAMT 2012-15'!$A$2:$A$98,0)),0) -> 0.98377153 | E28: =C28*$B$16*(1+$B$10)^(A28-$B$14)*D28 -> 0 | F28: =(1+$B$9)^(-A28) -> 0.62274974 | G28: =E28*F28 -> 0
A29: 8 | B29: =$B$3+A29 -> 53 | C29: =IF(AND(A29>=$B$14,B29<=$B$11),1,0) -> 0 | D29: =IFERROR(INDEX('IIAMT 2012-15'!$C$2:$C$98,MATCH(B29,'IIAMT 2012-15'!$A$2:$A$98,0))/INDEX('IIAMT 2012-15'!$C$2:$C$98,MATCH($B$3,'IIAMT 2012-15'!$A$2:$A$98,0)),0) -> 0.98063526 | E29: =C29*$B$16*(1+$B$10)^(A29-$B$14)*D29 -> 0 | F29: =(1+$B$9)^(-A29) -> 0.5820091 | G29: =E29*F29 -> 0
A30: 9 | B30: =$B$3+A30 -> 54 | C30: =IF(AND(A30>=$B$14,B30<=$B$11),1,0) -> 0 | D30: =IFERROR(INDEX('IIAMT 2012-15'!$C$2:$C$98,MATCH(B30,'IIAMT 2012-15'!$A$2:$A$98,0))/INDEX('IIAMT 2012-15'!$C$2:$C$98,MATCH($B$3,'IIAMT 2012-15'!$A$2:$A$98,0)),0) -> 0.97723834 | E30: =C30*$B$16*(1+$B$10)^(A30-$B$14)*D30 -> 0 | F30: =(1+$B$9)^(-A30) -> 0.54393374 | G30: =E30*F30 -> 0
A31: 10 | B31: =$B$3+A31 -> 55 | C31: =IF(AND(A31>=$B$14,B31<=$B$11),1,0) -> 0 | D31: =IFERROR(INDEX('IIAMT 2012-15'!$C$2:$C$98,MATCH(B31,'IIAMT 2012-15'!$A$2:$A$98,0))/INDEX('IIAMT 2012-15'!$C$2:$C$98,MATCH($B$3,'IIAMT 2012-15'!$A$2:$A$98,0)),0) -> 0.97355611 | E31: =C31*$B$16*(1+$B$10)^(A31-$B$14)*D31 -> 0 | F31: =(1+$B$9)^(-A31) -> 0.50834929 | G31: =E31*F31 -> 0
A32: 11 | B32: =$B$3+A32 -> 56 | C32: =IF(AND(A32>=$B$14,B32<=$B$11),1,0) -> 0 | D32: =IFERROR(INDEX('IIAMT 2012-15'!$C$2:$C$98,MATCH(B32,'IIAMT 2012-15'!$A$2:$A$98,0))/INDEX('IIAMT 2012-15'!$C$2:$C$98,MATCH($B$3,'IIAMT 2012-15'!$A$2:$A$98,0)),0) -> 0.96956356 | E32: =C32*$B$16*(1+$B$10)^(A32-$B$14)*D32 -> 0 | F32: =(1+$B$9)^(-A32) -> 0.4750928 | G32: =E32*F32 -> 0
... A101: 80 | B101: =$B$3+A101 -> 125 | C101: =IF(AND(A101>=$B$14,B101<=$B$11),1,0) -> 0 | D101: =IFERROR(INDEX('IIAMT 2012-15'!$C$2:$C$98,MATCH(B101,'IIAMT 2012-15'!$A$2:$A$98,0))/INDEX('IIAMT 2012-15'!$C$2:$C$98,MATCH($B$3,'IIAMT 2012-15'!$A$2:$A$98,0)),0) -> 0 | E101: =C101*$B$16*(1+$B$10)^(A101-$B$14)*D101 -> 0 | F101: =(1+$B$9)^(-A101) -> 0.0044596193 | G101: =E101*F101 -> 0

Sheet IIAMT 2012-15
A1: Age | B1: q(x): chance of dying within a year | C1: l(x): survivors out of 1.0 at age 20
A2: 20 | B2: 0.000284 | C2: 1
A3: 21 | B3: 0.000305 | C3: =C2*(1-B2) -> 0.999716
A4: 22 | B4: 0.000328 | C4: =C3*(1-B3) -> 0.99941109
A5: 23 | B5: 0.000353 | C5: =C4*(1-B4) -> 0.99908328
A6: 24 | B6: 0.000379 | C6: =C5*(1-B5) -> 0.9987306
A7: 25 | B7: 0.000407 | C7: =C6*(1-B6) -> 0.99835208
A8: 26 | B8: 0.000438 | C8: =C7*(1-B7) -> 0.99794576
A9: 27 | B9: 0.000471 | C9: =C8*(1-B8) -> 0.99750865
A10: 28 | B10: 0.000507 | C10: =C9*(1-B9) -> 0.99703883
A11: 29 | B11: 0.000545 | C11: =C10*(1-B10) -> 0.99653333
A12: 30 | B12: 0.000586 | C12: =C11*(1-B11) -> 0.99599022
A13: 31 | B13: 0.000631 | C13: =C12*(1-B12) -> 0.99540657
A14: 32 | B14: 0.000679 | C14: =C13*(1-B13) -> 0.99477847
... A97: 115 | B97: 0.99999 | C97: =C96*(1-B96) -> 6.0652039e-11
A98: 116 | C98: =C97*(1-B97) -> 6.0652039e-16
